bavest/__init__.py
bavest/api.py
bavest/errors.py
bavest/finance/__init__.py
bavest/finance/client/__init__.py
bavest/finance/client/bavest_client.py
bavest/finance/client/urls.py
bavest/finance/models/__init__.py
bavest/finance/models/v0/__init__.py
bavest/finance/models/v0/candle/__init__.py
bavest/finance/models/v0/candle/candle.py
bavest/finance/models/v0/etf/__init__.py
bavest/finance/models/v0/etf/country/__init__.py
bavest/finance/models/v0/etf/country/country.py
bavest/finance/models/v0/etf/holding/__init__.py
bavest/finance/models/v0/etf/holding/holding.py
bavest/finance/models/v0/etf/profile/__init__.py
bavest/finance/models/v0/etf/profile/profile.py
bavest/finance/models/v0/etf/sector/__init__.py
bavest/finance/models/v0/etf/sector/sector.py
bavest/finance/models/v0/forex/__init__.py
bavest/finance/models/v0/forex/forex.py
bavest/finance/models/v0/market/__init__.py
bavest/finance/models/v0/market/news.py
bavest/finance/models/v0/portfolio/__init__.py
bavest/finance/models/v0/portfolio/allocation/__init__.py
bavest/finance/models/v0/portfolio/allocation/allocation.py
bavest/finance/models/v0/portfolio/chart/__init__.py
bavest/finance/models/v0/portfolio/chart/chart.py
bavest/finance/models/v0/portfolio/metric/__init__.py
bavest/finance/models/v0/portfolio/metric/metric.py
bavest/finance/models/v0/portfolio/price/__init__.py
bavest/finance/models/v0/portfolio/price/price.py
bavest/finance/models/v0/portfolio/region/__init__.py
bavest/finance/models/v0/portfolio/region/region.py
bavest/finance/models/v0/portfolio/sector/__init__.py
bavest/finance/models/v0/portfolio/sector/sector.py
bavest/finance/models/v0/portfolio/stats/__init__.py
bavest/finance/models/v0/portfolio/stats/stats.py
bavest/finance/models/v0/quote/__init__.py
bavest/finance/models/v0/quote/quote.py
bavest/finance/models/v0/screener/__init__.py
bavest/finance/models/v0/screener/screener.py
bavest/finance/models/v0/search/__init__.py
bavest/finance/models/v0/search/search.py
bavest-1.0.1.dist-info/LICENSE.md
bavest-1.0.1.dist-info/WHEEL
bavest-1.0.1.dist-info/METADATA
bavest-1.0.1.dist-info/RECORD
