Metadata-Version: 2.1
Name: bavest
Version: 1.0.1
Summary: The Bavest Finance Python SDK
Author: William Todt
Author-email: william.todt@bavest.co
Requires-Python: >=3.8
Classifier: Programming Language :: Python :: 3
Classifier: Programming Language :: Python :: 3.8
Classifier: Programming Language :: Python :: 3.9
Classifier: Programming Language :: Python :: 3.10
Classifier: Programming Language :: Python :: 3.11
